scrapeDataQuotes.py
scrapeDataQuotes-0.0.5.dist-info/METADATA
scrapeDataQuotes-0.0.5.dist-info/WHEEL
scrapeDataQuotes-0.0.5.dist-info/top_level.txt
scrapeDataQuotes-0.0.5.dist-info/RECORD
