Metadata-Version: 2.1
Name: scrapeDataQuotes
Version: 0.0.5
Summary: HMTV live news scraping
Home-page: UNKNOWN
Author: Phani Siginamsetty
License: UNKNOWN
Keywords: web scraping
Platform: UNKNOWN
Classifier: Programming Language :: Python :: 3
Classifier: License :: OSI Approved :: MIT License
Classifier: Operating System :: OS Independent
Requires-Python: >=3.6
Requires-Dist: pandas
Requires-Dist: requests
Requires-Dist: bs4
